MANIFEST.in
setup.py
driver/acceleration.cpp
driver/acceleration.h
driver/buffer.cpp
driver/buffer.h
driver/context.cpp
driver/context.h
driver/destroyable.cpp
driver/destroyable.h
driver/geometry.cpp
driver/geometry.h
driver/geometry_group.cpp
driver/geometry_group.h
driver/geometry_instance.cpp
driver/geometry_instance.h
driver/group.cpp
driver/group.h
driver/main.cpp
driver/material.cpp
driver/material.h
driver/program.cpp
driver/program.h
driver/scoped.cpp
driver/scoped.h
driver/selector.cpp
driver/selector.h
driver/shared_includes.h
driver/texture_sampler.cpp
driver/texture_sampler.h
driver/transform.cpp
driver/transform.h
driver/variable.cpp
driver/variable.h
pyoptix/__init__.py
pyoptix/acceleration.py
pyoptix/buffer.py
pyoptix/compiler.py
pyoptix/context.py
pyoptix/entry_point.py
pyoptix/enums.py
pyoptix/geometry.py
pyoptix/geometry_group.py
pyoptix/geometry_instance.py
pyoptix/group.py
pyoptix/material.py
pyoptix/program.py
pyoptix/selector.py
pyoptix/texture_sampler.py
pyoptix/transform.py
pyoptix/utils.py
pyoptix/variable.py
pyoptix.egg-info/PKG-INFO
pyoptix.egg-info/SOURCES.txt
pyoptix.egg-info/dependency_links.txt
pyoptix.egg-info/requires.txt
pyoptix.egg-info/top_level.txt
pyoptix/mixins/__init__.py
pyoptix/mixins/bindless.py
pyoptix/mixins/destroyable.py
pyoptix/mixins/graphnode.py
pyoptix/mixins/hascontext.py
pyoptix/mixins/parent.py
pyoptix/mixins/scoped.py